word2number_es/__init__.py
word2number_es/w2n.py
word2number_es-1.0.1.dist-info/LICENSE.txt
word2number_es-1.0.1.dist-info/METADATA
word2number_es-1.0.1.dist-info/WHEEL
word2number_es-1.0.1.dist-info/top_level.txt
word2number_es-1.0.1.dist-info/RECORD
