Metadata-Version: 2.1
Name: word2number-es
Version: 1.0.1
Summary: Convert number words (eg. veintiuno) to numeric digits (spanish)
Home-page: https://github.com/Neuri-ai/w2n_es
Author: Neuri
Author-email: support@neuri.ai
License: The MIT License (MIT)
Keywords: numbers,convert,words,spanish
Classifier: Intended Audience :: Developers
Classifier: Programming Language :: Python
License-File: LICENSE.txt
